feature_selection_ga/__init__.py
feature_selection_ga/feature_selection_ga.py
feature_selection_ga/fitness_function.py
feature_selection_ga-0.1.3.dist-info/LICENSE
feature_selection_ga-0.1.3.dist-info/METADATA
feature_selection_ga-0.1.3.dist-info/WHEEL
feature_selection_ga-0.1.3.dist-info/top_level.txt
feature_selection_ga-0.1.3.dist-info/RECORD
